category_embedding/__init__.py
category_embedding/encoder.py
category_embedding/version.py
category_embedding-0.1.9.dist-info/licenses/LICENSE
category_embedding-0.1.9.dist-info/METADATA
category_embedding-0.1.9.dist-info/WHEEL
category_embedding-0.1.9.dist-info/top_level.txt
category_embedding-0.1.9.dist-info/RECORD
