Metadata-Version: 2.4
Name: category-embedding
Version: 0.1.9
Summary: A Keras-based entity embedding encoder for tabular ML and GBM pipelines
Author-email: Danu Andries <danu@andries.lu>
License: MIT License 
Project-URL: Homepage, https://github.com/Karabush/category-embedding
Project-URL: Repository, https://github.com/Karabush/category-embedding
Keywords: machine learning,deep learning,tabular data,categorical encoding,entity embeddings,category embeddings,neural encoder,keras,tensorflow,scikit-learn,sklearn transformer,feature engineering,gradient boosting,lightgbm,xgboost,embeddings for gbm,tabular embeddings,ml pipelines,optuna tuning,high-cardinality features,feature preprocessing
Classifier: Programming Language :: Python :: 3
Classifier: Intended Audience :: Developers
Classifier: Intended Audience :: Science/Research
Classifier: Topic :: Scientific/Engineering :: Artificial Intelligence
Requires-Python: >=3.9
License-File: LICENSE
Requires-Dist: numpy>=1.22
Requires-Dist: pandas>=1.5
Requires-Dist: scikit-learn>=1.2
Requires-Dist: tensorflow>=2.12
Dynamic: license-file
